README
setup.cfg
setup.py
rfm12_mqtt_gateway/__init__.py
rfm12_mqtt_gateway/gateway.py
rfm12_mqtt_gateway/nodes.py
rfm12_mqtt_gateway/parser.py
rfm12_mqtt_gateway/textfilewriter.py
rfm12_mqtt_gateway.egg-info/PKG-INFO
rfm12_mqtt_gateway.egg-info/SOURCES.txt
rfm12_mqtt_gateway.egg-info/dependency_links.txt
rfm12_mqtt_gateway.egg-info/entry_points.txt
rfm12_mqtt_gateway.egg-info/requires.txt
rfm12_mqtt_gateway.egg-info/top_level.txt
test/test_node_definition.py
test/test_parser.py