Metadata-Version: 1.1
Name: rfm12-mqtt-gateway
Version: 0.1.0
Summary: Two-way RFM12 to MQTT gateway
Home-page: https://github.com/ricklupton/rfm12-mqtt-gateway
Author: Rick Lupton
Author-email: r.lupton@gmail.com
License: MIT
Keywords: rfm12 mqtt gateway openenergymonitor raspberrypi
Platform: UNKNOWN
Classifier: Development Status :: 3 - Alpha
Classifier: Intended Audience :: Developers
Classifier: Intended Audience :: End Users/Desktop
Classifier: License :: OSI Approved :: MIT License
Classifier: Programming Language :: Python :: 3
Classifier: Programming Language :: Python :: 3.4
